{
  "MySnip": {
    "prefix": "mysnip", 
    "body": [
    "<!-- Matvii Khadzhynov Ekfu-24/1 -->",
	"<!DOCTYPE html>",
	"<html lang=\"en\">",
	"<head>",
    "   <meta charset=\"UTF-8\">",
    "   <meta name=\"viewport\" content=\"width=device-width, initial-scale=1.0\">",
    "   <title>Document</title>",
	"</head>",
	"<body>",
  "    <p><b>AFSAUFkddsa</b> dsaas <u>daslkdjsalDSADAS</u> <i>skafAFA</i> <i><b>fafjSADS</b></i>, <u><i>osDSAfsaio</i></u> <b><u>djdSAJOSDOPAS</u></b> <b><i><u>jfsadADSADSAaojfsai</u></i></b></p>",
	"</body>",
	"</html>"
    ],
    "description": "My snip"
  },
  "BasicSnip": {
    "prefix": "basic_snip", 
    "body": [
    "<!DOCTYPE html>",
    "<html lang=\"lt\">",
    "<head>",
    "    <meta charset=\"UTF-8\">",
    "    <meta name=\"author\" content=\"MatKhad\">",
    "    <meta name=\"description\" content=\"Basic HTML document for lab assignment\">",
    "    <title>First Lab</title>",
    "    <!-- MatKhad 20242846-->",
    "    <link>",
    "</head>",
    "<body>",
    "",
    "</body>",
    "</html>"
    ],
    "description": "Basic Snip"
  }
}
